EgyBestAPI/__init__.py
Py_EgyBest_Api-22.9.16.dist-info/LICENSE
Py_EgyBest_Api-22.9.16.dist-info/METADATA
Py_EgyBest_Api-22.9.16.dist-info/WHEEL
Py_EgyBest_Api-22.9.16.dist-info/top_level.txt
Py_EgyBest_Api-22.9.16.dist-info/RECORD
