Metadata-Version: 2.1
Name: Py-EgyBest-Api
Version: 22.9.16
Summary: Asynchronous Python Wrapper For EgyBest-API.
Home-page: https://github.com/AmineSoukara/Py-EgyBest-Api
Author: AmineSoukara
Author-email: AmineSoukara@gmail.com
License: MIT
Project-URL: Source, https://github.com/AmineSoukara/Py-EgyBest-Api
Project-URL: Documentation, https://github.com/AmineSoukara/Py-EgyBest-Api#readme
Project-URL: Tracker, https://github.com/AmineSoukara/Py-EgyBest-Api/issues
Keywords: EgyBest Api Scrapper Python
Classifier: Development Status :: 5 - Production/Stable
Classifier: Intended Audience :: Developers
Classifier: Topic :: Software Development :: Build Tools
Classifier: Natural Language :: English
Classifier: License :: OSI Approved :: MIT License
Classifier: Operating System :: OS Independent
Classifier: Programming Language :: Python :: 3.8
Classifier: Programming Language :: Python :: 3.9
Classifier: Topic :: Internet
Requires-Python: >=3.8
License-File: LICENSE
Requires-Dist: aiohttp
Requires-Dist: aiofiles
Requires-Dist: dotmap
Requires-Dist: requests
Requires-Dist: urllib3
